{
  "menu": [
    {
      "url": "/",
      "name": "Beranda",
      "icon": "menu-icon tf-icons bx bx-home-smile",
      "slug": "beranda"
    },
    {
      "menuHeader": "Manajemen & Data"
    },
    {
      "url": "toko-supplier",
      "name": "Toko & Supplier",
      "icon": "menu-icon tf-icons bx bx-home-circle",
      "slug": "toko-supplier"
    },
    {
      "url": "products",
      "name": "Produk",
      "icon": "menu-icon tf-icons bx bx-box",
      "slug": "products",
      "badge": []
    },
    {
      "url": "metode-pembayaran",
      "name": "Metode Pembayaran",
      "icon": "menu-icon tf-icons bx bx-credit-card",
      "slug": "metode-pembayaran"
    },
    {
      "url": "karyawan",
      "name": "Karyawan",
      "icon": "menu-icon tf-icons bx bx-male-female",
      "slug": "karyawan"
    },
    {
      "url": "gaji",
      "name": "Gaji",
      "icon": "menu-icon tf-icons bx bx-money",
      "slug": "gaji"
    },
    {
      "url": "users",
      "name": "Pengguna",
      "icon": "menu-icon tf-icons bx bx-group",
      "slug": "users"
    },
    {
      "menuHeader": "Transaksi"
    },
    {
      "url": "sales",
      "name": "Penjualan",
      "icon": "menu-icon tf-icons bx bx-cart-add",
      "slug": "sales"
    },
    {
      "url": "kulak",
      "name": "Pembelian Bahan",
      "icon": "menu-icon tf-icons bx bx-cart-download",
      "slug": "kulak"
    },
    {
      "url": "pengambilan-bahan",
      "name": "Pengambilan Bahan",
      "icon": "menu-icon tf-icons bx bx-cart-alt",
      "slug": "pengambilan-bahan"
    },
    {
      "url": "toko-income",
      "name": "Pemasukan Toko",
      "icon": "menu-icon tf-icons bx bx-archive-in",
      "slug": "toko-income"
    },
    {
      "url": "pengeluaran",
      "name": "Pengeluaran Lainnya",
      "icon": "menu-icon tf-icons bx bx-upload",
      "slug": "pengeluaran"
    },
    {
      "menuHeader": "Laporan"
    },
    {
      "url": "reports",
      "name": "Laporan Keuangan",
      "icon": "menu-icon tf-icons bx bx-line-chart",
      "slug": "reports"
    },
    {
      "url": "toko-reports",
      "name": "Laporan Toko",
      "icon": "menu-icon tf-icons bx bx-bar-chart-alt-2",
      "slug": "toko-reports"
    }
  ]
}